fence/__init__.py
fence/chains.py
fence/links.py
fence/parsers.py
fence/agents/__init__.py
fence/agents/agent.py
fence/agents/base.py
fence/agents/chat.py
fence/agents/bedrock/__init__.py
fence/agents/bedrock/agent.py
fence/agents/bedrock/models.py
fence/benchmark/prompts.py
fence/benchmark/run.py
fence/embeddings/base.py
fence/embeddings/bedrock/__init__.py
fence/embeddings/bedrock/base.py
fence/embeddings/bedrock/nova.py
fence/embeddings/bedrock/titan.py
fence/embeddings/google/__init__.py
fence/embeddings/google/gemini.py
fence/embeddings/mistral/__init__.py
fence/embeddings/mistral/mistral.py
fence/embeddings/ollama/ollama.py
fence/embeddings/openai/openai.py
fence/mcp/client.py
fence/mcp/tool.py
fence/mcp/utils.py
fence/memory/__init__.py
fence/memory/agentcore.py
fence/memory/base.py
fence/memory/dynamodb.py
fence/memory/sqlite.py
fence/models/__init__.py
fence/models/base.py
fence/models/anthropic/__init__.py
fence/models/anthropic/claude.py
fence/models/bedrock/__init__.py
fence/models/bedrock/base.py
fence/models/bedrock/claude.py
fence/models/bedrock/nova.py
fence/models/gemini/__init__.py
fence/models/gemini/gemini.py
fence/models/mistral/__init__.py
fence/models/mistral/mistral.py
fence/models/ollama/__init__.py
fence/models/ollama/ollama.py
fence/models/openai/__init__.py
fence/models/openai/gpt.py
fence/prompts/agents.py
fence/streaming/base.py
fence/templates/__init__.py
fence/templates/base.py
fence/templates/messages.py
fence/templates/models.py
fence/templates/string.py
fence/tools/base.py
fence/tools/math.py
fence/tools/scratch.py
fence/tools/text.py
fence/troupe/round_table.py
fence/utils/__init__.py
fence/utils/base.py
fence/utils/docstring_parser.py
fence/utils/logger.py
fence/utils/nlp.py
fence/utils/optim.py
fence/utils/shortcuts.py
fence_llm-2.1.3.dist-info/METADATA
fence_llm-2.1.3.dist-info/WHEEL
fence_llm-2.1.3.dist-info/licenses/LICENSE.txt
fence_llm-2.1.3.dist-info/RECORD
