Metadata-Version: 2.4
Name: fence-llm
Version: 2.1.3
Summary: The bloat moat! - A lightweight LLM and Agent interaction library
Project-URL: Repository, https://github.com/WouterDurnez/fence
Project-URL: Homepage, https://github.com/WouterDurnez/fence
Project-URL: Documentation, https://github.com/WouterDurnez/fence
Author-email: "wouter.durnez" <wouter.durnez@gmail.com>
License: MIT
License-File: LICENSE.txt
Keywords: ai,anthropic,api,claude,fence,gpt,language,llm,model,nlp,openai,wrapper
Classifier: Intended Audience :: Developers
Classifier: Intended Audience :: Science/Research
Classifier: License :: OSI Approved :: MIT License
Classifier: Programming Language :: Python
Classifier: Programming Language :: Python :: 3
Classifier: Programming Language :: Python :: 3 :: Only
Classifier: Programming Language :: Python :: 3.12
Classifier: Programming Language :: Python :: 3.13
Classifier: Programming Language :: Python :: Implementation :: CPython
Classifier: Topic :: Scientific/Engineering
Classifier: Topic :: Software Development
Requires-Python: >=3.11
Requires-Dist: boto3>=1.34.100
Requires-Dist: mcp>=1.23.0
Requires-Dist: numexpr>=2.10.1
Requires-Dist: pydantic>=2.11.4
Requires-Dist: requests>=2.32.4
